clro/__init__.py
clro/lib.py
clro-0.0.2.dist-info/LICENSE
clro-0.0.2.dist-info/METADATA
clro-0.0.2.dist-info/WHEEL
clro-0.0.2.dist-info/top_level.txt
clro-0.0.2.dist-info/RECORD
